aic_utils/__init__.py
aic_utils/aic.py
aic_utils/dataset_converter.py
aic_utils/gitlab_init.py
aic_utils/gitlabmanager.py
aic_utils/slack_logger.py
aic_utils-2.0.2.dist-info/METADATA
aic_utils-2.0.2.dist-info/WHEEL
aic_utils-2.0.2.dist-info/top_level.txt
aic_utils-2.0.2.dist-info/RECORD
