Metadata-Version: 2.1
Name: aic_utils
Version: 2.0.2
Summary: AIC API wrapper and GitLab integration framework for pipeline management
Home-page: https://github.com/dylandoyle11/aic_utils
Author: Dylan D
Author-email: dylan.doyle@jdpa.com
Keywords: aic gitlab pipeline automation devops
Classifier: Development Status :: 4 - Beta
Classifier: Intended Audience :: Developers
Classifier: Topic :: Software Development :: Libraries :: Python Modules
Classifier: Programming Language :: Python :: 3
Classifier: Programming Language :: Python :: 3.8
Classifier: Programming Language :: Python :: 3.9
Classifier: Programming Language :: Python :: 3.10
Classifier: Programming Language :: Python :: 3.11
Classifier: License :: OSI Approved :: MIT License
Classifier: Operating System :: OS Independent
Requires-Python: >=3.8
Requires-Dist: requests >=2.25.0
Requires-Dist: PyYAML >=5.4.0
Requires-Dist: pandas >=1.3.0
Requires-Dist: slack-sdk >=3.0.0
